alembic_autogen_check.py
alembic_autogen_check-1.1.1.dist-info/LICENSE
alembic_autogen_check-1.1.1.dist-info/METADATA
alembic_autogen_check-1.1.1.dist-info/WHEEL
alembic_autogen_check-1.1.1.dist-info/entry_points.txt
alembic_autogen_check-1.1.1.dist-info/top_level.txt
alembic_autogen_check-1.1.1.dist-info/RECORD
