Metadata-Version: 2.1
Name: alembic-autogen-check
Version: 1.1.1
Summary: CLI to check with alembic migrations are in sync with your SQLAlchemy models.
Home-page: https://github.com/4Catalyzer/alembic-autogen-check
Author: 4Catalyzer
Author-email: sloria@butterflynetinc.com
License: MIT
Keywords: sqlalchemy alembic
Platform: UNKNOWN
Classifier: License :: OSI Approved :: MIT License
Classifier: Programming Language :: Python :: 3
Classifier: Programming Language :: Python :: 3.6
Classifier: Programming Language :: Python :: 3.7
Requires-Python: >=3.6
Requires-Dist: alembic
Requires-Dist: click (>=7.0)
Provides-Extra: dev
Requires-Dist: pytest ; extra == 'dev'
Requires-Dist: fourmat (==0.2.0) ; extra == 'dev'
Requires-Dist: pre-commit (==1.16.1) ; extra == 'dev'
Requires-Dist: tox ; extra == 'dev'
Provides-Extra: lint
Requires-Dist: fourmat (==0.2.0) ; extra == 'lint'
Requires-Dist: pre-commit (==1.16.1) ; extra == 'lint'
Provides-Extra: tests
Requires-Dist: pytest ; extra == 'tests'
